{
    "identifier": "ChangeEmail",
    "shouldHideActions": ["skip"],
    "progressMarkers": [],
    "steps": [{
        "identifier": "provide_email",
        "type": "requestEmailForm",
        "title": "Get compensated for participating!",
        "text": "In the app, you can enroll in optional sub-studies where you may be paid for participating. Please enter your email below where we would send your compensation via digital gift cards.",
        "inputFields": [{
            "type": "string",
            "textFieldOptions": {
                "keyboardType": "emailAddress",
                "textValidator": "^[A-Za-z0-9+_.-]+@(.+)$",
                "invalidMessage": "Please enter a valid email address."
            },
            "uiHint": "textfield",
            "placeholder": "Email address"
        }],
        "image": {
            "type": "fetchable",
            "imageName": "CompensateIcon",
            "placementType": "iconBefore"
        },
        "actions": {
            "goForward": {
                "type": "default",
                "buttonTitle": "Submit"
            }
        }
    }]
}
